setup.cfg
setup.py
src/bokto/__init__.py
src/bokto.egg-info/PKG-INFO
src/bokto.egg-info/SOURCES.txt
src/bokto.egg-info/dependency_links.txt
src/bokto.egg-info/top_level.txt