Metadata-Version: 2.1
Name: bokto
Version: 0.0.0
Summary: Example Python Package
Author: Ryan Petrello
Author-email: rpetrello@missioncloud.com
Requires-Python: >=3.6
